{
  "waves_done": ["1-11","12-dedup","13-skeptical-reader","g4a-deep-explanation","g4b-misconceptions","g4c-analogy","g4d-projects","g4e-research-frontier","g4f-fact-check","g4g-terminology","g5a-prose-clarity","g5b-engagement","g5c-style-voice","g5d-aha-moments","g5e-memorability","g6a-svg-diagrams","g6b-self-containment"],
  "current": {
    "run_id": "wf_2d171c5b-c0f",
    "task_id": "w350mth8t",
    "script": "scripts/g6-figure-facts-workflow.js",
    "model": "opus-4-8",
    "resume": "Workflow({ scriptPath: 'E:/Projects/Books/EmbodiedAI/scripts/g6-figure-facts-workflow.js', resumeFromRunId: 'wf_2d171c5b-c0f' })"
  },
  "queue_after_current": [
    "scripts/g7-skeptical-reader-workflow.js",
    "scripts/pack-p1b-workflow.js",
    "scripts/pack-p3-workflow.js",
    "scripts/pack-p4a-workflow.js",
    "scripts/pack-p5-workflow.js",
    "scripts/pack-p6-workflow.js",
    "scripts/pack-p7-workflow.js"
  ]
}
